glados_chat_lib/__init__.py
glados_chat_lib/audio.py
glados_chat_lib/chat.py
glados_chat_lib/cli.py
glados_chat_lib/config.py
glados_chat_lib/sarcasm.py
glados_chat_lib/stt.py
glados_chat_lib/tts.py
glados_chat_lib/voice_mod.py
glados_chat_lib-0.1.dist-info/METADATA
glados_chat_lib-0.1.dist-info/WHEEL
glados_chat_lib-0.1.dist-info/entry_points.txt
glados_chat_lib-0.1.dist-info/top_level.txt
glados_chat_lib-0.1.dist-info/RECORD
