Metadata-Version: 2.4
Name: glados-chat-lib
Version: 0.1
Summary: Talk with GLaDOS using Ollama + Piper TTS + Whisper STT
Author: AmongTheCouch Studios
License: MIT
Requires-Python: >=3.9
Requires-Dist: ollama
Requires-Dist: httpx
Requires-Dist: sounddevice
Requires-Dist: soundfile
Requires-Dist: numpy
Requires-Dist: huggingface_hub
Requires-Dist: piper-tts
Requires-Dist: faster-whisper
Requires-Dist: SpeechRecognition
Requires-Dist: webrtcvad-wheels
